onnxtk/__init__.py
onnxtk/decast.py
onnxtk/float16.py
onnxtk/optimizer.py
onnxtk-0.0.1.dist-info/METADATA
onnxtk-0.0.1.dist-info/RECORD
onnxtk-0.0.1.dist-info/WHEEL
onnxtk-0.0.1.dist-info/top_level.txt
